pixoo_spotify/__init__.py
pixoo_spotify/app.py
pixoo_spotify/cli.py
pixoo_spotify/config.py
pixoo_spotify/dummy.py
pixoo_spotify/fonts.py
pixoo_spotify/gif.py
pixoo_spotify/langs.py
pixoo_spotify/models.py
pixoo_spotify/net.py
pixoo_spotify/paths.py
pixoo_spotify/pixoo.py
pixoo_spotify/server.py
pixoo_spotify/spotify.py
pixoo_spotify/ui.py
pixoo_spotify/fonts/misaki/misaki.txt
pixoo_spotify/fonts/misaki/misaki_gothic.ttf
pixoo_spotify/fonts/misaki/readme.txt
pixoo_spotify-0.0.4.dist-info/licenses/LICENSE
pixoo_spotify-0.0.4.dist-info/METADATA
pixoo_spotify-0.0.4.dist-info/WHEEL
pixoo_spotify-0.0.4.dist-info/entry_points.txt
pixoo_spotify-0.0.4.dist-info/top_level.txt
pixoo_spotify-0.0.4.dist-info/RECORD
